eip_auditor
