Metadata-Version: 1.1
Name: eip-auditor
Version: 1.0.1
Summary: An AWS EIP Auditor
Home-page: https://github.com/SpekoTechnologies/eip-auditor
Author: Speko Technologies
Author-email: info@speko.io
License: UNKNOWN
Keywords: eip auditor aws vpc elastic ip addresses
Platform: UNKNOWN
Classifier: Development Status :: 3 - Alpha
Classifier: Intended Audience :: Developers
Classifier: Topic :: Software Development :: Build Tools
Classifier: License :: OSI Approved :: MIT License
Classifier: Programming Language :: Python :: 2
Classifier: Programming Language :: Python :: 2.7
